pywordle/__init__.py
pywordle/wordle.py
pywordle/words/words.en.txt
pywordle/words/words.es.txt
pywordle/words/words.fr.txt
pywordle/words/words.small.en.txt
pywordle-0.3.5.dist-info/METADATA
pywordle-0.3.5.dist-info/WHEEL
pywordle-0.3.5.dist-info/entry_points.txt
pywordle-0.3.5.dist-info/RECORD
