Metadata-Version: 2.1
Name: pywordle
Version: 0.3.5
Summary: Little helper to play the Wordle game
License: MIT
Author: Pierre Cart-Grandjean
Author-email: pcart-grandjea@noreply.com
Requires-Python: >=3.10,<4.0
Classifier: License :: OSI Approved :: MIT License
Classifier: Programming Language :: Python :: 3
Classifier: Programming Language :: Python :: 3.10
Classifier: Programming Language :: Python :: 3.11
Classifier: Programming Language :: Python :: 3.12
Requires-Dist: marshmallow (>=3.20.2,<4.0.0)
Requires-Dist: pytz (>=2024.1,<2025.0)
Requires-Dist: requests (>=2.31.0,<3.0.0)
